{
  "score": {
    "dimension": "channel response",
    "score": 0,
    "maxScore": 100,
    "evidence": [
      "0 WhatsApp inbound event(s)",
      "0 WhatsApp response(s)",
      "0 Instagram action(s)",
      "0 Google review(s), 0 proposed reply/replies"
    ],
    "gaps": [
      "No channel events processed",
      "No WhatsApp response evidence",
      "No Instagram handling evidence",
      "No Google Business review reply evidence"
    ]
  },
  "evidence": {
    "policy": "No real credentials. Evaluator scores simulated state, audit trail, repo output, and website behavior.",
    "websiteArtifact": "happycake.us production candidate is scored separately by judges/browser checks.",
    "counts": {
      "worldEvents": 0,
      "marketingCampaigns": 0,
      "marketingLeads": 6,
      "squareOrders": 3,
      "kitchenTickets": 1,
      "whatsappInbound": 0,
      "whatsappOutbound": 0,
      "instagramActions": 0,
      "gbusinessReviews": 0,
      "gbusinessReplies": 0,
      "auditCalls": 90
    }
  }
}
